kmapper/__init__.py
kmapper/_version.py
kmapper/adapter.py
kmapper/cover.py
kmapper/drawing.py
kmapper/jupyter.py
kmapper/kmapper.py
kmapper/nerve.py
kmapper/plotlyviz.py
kmapper/utils.py
kmapper/visuals.py
kmapper/static/FileSaver.min.js
kmapper/static/d3-lasso.js
kmapper/static/d3.min.js
kmapper/static/kmapper-vNext.js
kmapper/static/kmapper.js
kmapper/static/logo.png
kmapper/static/style.css
kmapper/templates/base.html
kmapper/templates/cluster_tooltip.html
kmapper/templates/help.html
kmapper/templates/summary_data.html
kmapper/templates/toolbar.html
kmapper-2.1.0.dist-info/AUTHORS.md
kmapper-2.1.0.dist-info/LICENSE.txt
kmapper-2.1.0.dist-info/METADATA
kmapper-2.1.0.dist-info/WHEEL
kmapper-2.1.0.dist-info/top_level.txt
kmapper-2.1.0.dist-info/RECORD
