Metadata-Version: 2.1
Name: kmapper
Version: 2.1.0
Summary: Python implementation of Mapper algorithm for Topological Data Analysis.
Home-page: http://kepler-mapper.scikit-tda.org
Author: HJ van Veen, Nathaniel Saul, David Eargle, Sam Mangham
Author-email: info@mlwave.com, nat@saulgill.com
License: MIT
Keywords: mapper,topology data analysis,algebraic topology,unsupervised learning
Classifier: Development Status :: 4 - Beta
Classifier: Intended Audience :: Science/Research
Classifier: Intended Audience :: Education
Classifier: Intended Audience :: Financial and Insurance Industry
Classifier: Intended Audience :: Healthcare Industry
Classifier: Topic :: Scientific/Engineering :: Information Analysis
Classifier: Topic :: Scientific/Engineering :: Mathematics
Classifier: License :: OSI Approved :: MIT License
Classifier: Programming Language :: Python :: 3.6
Classifier: Programming Language :: Python :: 3.7
Classifier: Programming Language :: Python :: 3.8
Requires-Python: >=3.6
License-File: LICENSE.txt
License-File: AUTHORS.md
Requires-Dist: scikit-learn
Requires-Dist: numpy
Requires-Dist: scipy
Requires-Dist: Jinja2
Provides-Extra: testing
Requires-Dist: pytest; extra == "testing"
Requires-Dist: networkx; extra == "testing"
Requires-Dist: matplotlib; extra == "testing"
Requires-Dist: igraph; extra == "testing"
Requires-Dist: plotly; extra == "testing"
Requires-Dist: ipywidgets; extra == "testing"
Provides-Extra: docs
Requires-Dist: sktda_docs_config; extra == "docs"
Requires-Dist: sphinx; extra == "docs"
Requires-Dist: pandas; extra == "docs"
Requires-Dist: sphinx-gallery; extra == "docs"
Requires-Dist: networkx; extra == "docs"
Requires-Dist: matplotlib; extra == "docs"
Requires-Dist: igraph; extra == "docs"
Requires-Dist: plotly; extra == "docs"
Requires-Dist: ipykernel; extra == "docs"
Requires-Dist: ipywidgets; extra == "docs"
Requires-Dist: ipython; extra == "docs"
Requires-Dist: nbsphinx; extra == "docs"
